se2dataanalysis/__init__.py
se2dataanalysis/py.typed
se2dataanalysis/stats.py
se2dataanalysis/tools.py
se2dataanalysis-0.0.1.dist-info/METADATA
se2dataanalysis-0.0.1.dist-info/WHEEL
se2dataanalysis-0.0.1.dist-info/licenses/LICENSE.rst
se2dataanalysis-0.0.1.dist-info/RECORD
